README.md
setup.py
myNeuropsydia/__init__.py
myNeuropsydia/ask.py
myNeuropsydia/choice.py
myNeuropsydia/core.py
myNeuropsydia/fill_form.py
myNeuropsydia/image.py
myNeuropsydia/io.py
myNeuropsydia/meta.py
myNeuropsydia/miscellaneous.py
myNeuropsydia/path.py
myNeuropsydia/procedures.py
myNeuropsydia/scale.py
myNeuropsydia/start.py
myNeuropsydia/write.py
myNeuropsydia/__pycache__/__init__.cpython-38.pyc
myNeuropsydia/__pycache__/__init__.cpython-39.pyc
myNeuropsydia/__pycache__/ask.cpython-38.pyc
myNeuropsydia/__pycache__/ask.cpython-39.pyc
myNeuropsydia/__pycache__/choice.cpython-38.pyc
myNeuropsydia/__pycache__/choice.cpython-39.pyc
myNeuropsydia/__pycache__/core.cpython-38.pyc
myNeuropsydia/__pycache__/core.cpython-39.pyc
myNeuropsydia/__pycache__/fill_form.cpython-38.pyc
myNeuropsydia/__pycache__/fill_form.cpython-39.pyc
myNeuropsydia/__pycache__/image.cpython-38.pyc
myNeuropsydia/__pycache__/image.cpython-39.pyc
myNeuropsydia/__pycache__/io.cpython-38.pyc
myNeuropsydia/__pycache__/io.cpython-39.pyc
myNeuropsydia/__pycache__/meta.cpython-38.pyc
myNeuropsydia/__pycache__/meta.cpython-39.pyc
myNeuropsydia/__pycache__/miscellaneous.cpython-38.pyc
myNeuropsydia/__pycache__/miscellaneous.cpython-39.pyc
myNeuropsydia/__pycache__/path.cpython-38.pyc
myNeuropsydia/__pycache__/path.cpython-39.pyc
myNeuropsydia/__pycache__/procedures.cpython-38.pyc
myNeuropsydia/__pycache__/procedures.cpython-39.pyc
myNeuropsydia/__pycache__/scale.cpython-38.pyc
myNeuropsydia/__pycache__/scale.cpython-39.pyc
myNeuropsydia/__pycache__/screen.cpython-38.pyc
myNeuropsydia/__pycache__/screen.cpython-39.pyc
myNeuropsydia/__pycache__/start.cpython-38.pyc
myNeuropsydia/__pycache__/start.cpython-39.pyc
myNeuropsydia/__pycache__/write.cpython-38.pyc
myNeuropsydia/__pycache__/write.cpython-39.pyc
myNeuropsydia/files/__init__.py
myNeuropsydia/files/__pycache__/__init__.cpython-38.pyc
myNeuropsydia/files/binary/__init__.py
myNeuropsydia/files/binary/absorption_desk.png
newNeuropsydia.egg-info/PKG-INFO
newNeuropsydia.egg-info/SOURCES.txt
newNeuropsydia.egg-info/dependency_links.txt
newNeuropsydia.egg-info/requires.txt
newNeuropsydia.egg-info/top_level.txt