Metadata-Version: 2.1
Name: newNeuropsydia
Version: 0.1.1
Summary: Partially fixed version of Neuropsydia library, a Python module for creating experiments, tasks and questionnaires
Author: Laborde
License: ENS_Paris_Saclay
